{"id":20043,"title":"Hjemmelavet rugbrød","image":"https://images.unsplash.com/photo-1509440159596-0249088772ff?w=400&q=80","readyInMinutes":180,"servings":12,"ingredients":["500 g rugmel","200 g blandede kerner (solsikke, hørfrø, græskarkerner)","2 dl surdej (eller 1 pose gær)","1 spsk salt","1 spsk mørk sirup","5 dl lunkent vand"],"steps":["Bland rugmel, kerner og salt. Tilsæt surdej eller gær, sirup og vand. Rør godt til en tyk, klistret dej.","Hæld dejen i en smurt rugbrødsform. Glat toppen med en våd ske.","Dæk med film og lad hæve 2-3 timer ved stuetemperatur (eller natten over i køleskab).","Forvarm ovnen til 180°C. Bag rugbrødet i 1 time til 1 time 15 minutter.","Lad brødet afkøle helt på en bagerist inden opskæring — mindst 4 timer."]}
