{"id":635263,"title":"Svart Cajun-kylling","titleEn":"Blackened Cajun Chicken","image":"https://img.spoonacular.com/recipes/635263-556x370.jpg","readyInMinutes":45,"servings":4,"ingredients":["1 tsk knust laubladblad","2,25 tsk sort peber","1 spsk brunkulør sukker","1 tsk cayennepeber","1 tsk tørret rosmarin knust","1,5 tsk tørret timian","1 spsk tør sennep","1 tsk hvidløgspulver","1 tsk malet spidskommen","1 tsk løgpulver","1 spsk paprika","7,5 tsk salt","1600 g kylling"],"steps":["Bland alle krydderierne sammen. Krydderblandingen er nok til 2 høns. Den kan laves på forhånd og opbevares i en lufttæt beholder indtil den bruges.","Læg kyllingen på en 33 x 23 x 5 cm bageplade. Gnid den halvt med krydderblandingen. Dæk til og stil i køl natten over. Gril med låg over medium gløder, vend en gang, i 30 til 45 minutter eller indtil saften løber klart ud. Denne opskrift giver 4 portioner."]}