{"id":649062,"title":"Koreansk Perilla Pesto","titleEn":"Korean Perilla Pesto","image":"https://img.spoonacular.com/recipes/649062-556x370.jpg","readyInMinutes":45,"servings":8,"ingredients":["1 pakke friske sesamblad, cirka 25 til 30 blade.","1,2 dl pinjekerner, ristet på panden uden olie til de bliver lidt brune","2 spsk hakket hvidløg,","1,8 dl ekstra jomfru olivenolie—det bedste du har råd til","1,2 tsk salt,","0,5 tsk sort peber"],"steps":["Læg alle ingredienserne i en køkkenmaskine og blend alt sammen til det bliver en glat pasta.","Bland det i en skål med noget friskkogt pasta efter eget valg og servér, garneret med nogle tiloversblevne pinjekerner."]}